{"version": "0.3.3", "flags": {}, "shapes": [{"label": "date", "text": "", "points": [[363.5338753387534, 46.94630192502536], [505.2605497483546, 104.00810536980751]], "group_id": null, "shape_type": "rectangle", "flags": {}}, {"label": "sign", "text": "", "points": [[239.15137437088654, 247.1813576494428], [504.7650019357336, 395.54204660587635]], "group_id": null, "shape_type": "rectangle", "flags": {}}, {"label": "micra", "text": "", "points": [[9.712737127371284, 436.0040526849038], [163.8281068524971, 478.54103343465044]], "group_id": null, "shape_type": "rectangle", "flags": {}}, {"label": "acc_info", "text": "", "points": [[14.668215253581119, 241.9939209726444], [146.97948122338366, 339.5177304964539]], "group_id": null, "shape_type": "rectangle", "flags": {}}, {"label": "bank_name", "text": "", "points": [[23.58807588075882, 17.896656534954435], [162.83701122725515, 89.48328267477206]], "group_id": null, "shape_type": "rectangle", "flags": {}}, {"label": "pay_to", "text": "", "points": [[12.686024003097186, 110.2330293819656], [300.5993031358885, 157.95744680851067]], "group_id": null, "shape_type": "rectangle", "flags": {}}, {"label": "amount", "text": "", "points": [[365.0205187766163, 174.55724417426546], [505.2605497483546, 226.43161094224928]], "group_id": null, "shape_type": "rectangle", "flags": {}}, {"label": "amount_words", "text": "", "points": [[13.181571815718167, 158.99493414387032], [356.5962059620596, 211.90678824721383]], "group_id": null, "shape_type": "rectangle", "flags": {}}], "imagePath": "20230718120200F-2.JPG", "imageData": null, "imageHeight": 512, "imageWidth": 512}