{"version": "0.3.3", "flags": {}, "shapes": [{"label": "bank_name", "text": "", "points": [[23.33413468586006, 11.980567000799487], [144.4204559891329, 94.89469692310848]], "group_id": null, "shape_type": "rectangle", "flags": {}}, {"label": "date", "text": "", "points": [[364.57740381326533, 38.219215710390934], [505.17763640094995, 98.04333476825944]], "group_id": null, "shape_type": "rectangle", "flags": {}}, {"label": "amount", "text": "", "points": [[363.57669041406473, 161.01609167127893], [504.67727970134956, 225.03839452268213]], "group_id": null, "shape_type": "rectangle", "flags": {}}, {"label": "sign", "text": "", "points": [[239.9885856127904, 241.83112969682062], [503.67656630214896, 383.51983272861446]], "group_id": null, "shape_type": "rectangle", "flags": {}}, {"label": "acc_info", "text": "", "points": [[55.85732015987963, 257.5743189225755], [210.96789703597292, 357.281184019023]], "group_id": null, "shape_type": "rectangle", "flags": {}}, {"label": "pay_to", "text": "", "points": [[16.329140891455847, 104.3406104585614], [358.57312341806175, 150.52063218744237]], "group_id": null, "shape_type": "rectangle", "flags": {}}, {"label": "amount_words", "text": "", "points": [[16.829497591056146, 147.3719943422914], [333.55528843804666, 210.34475124531087]], "group_id": null, "shape_type": "rectangle", "flags": {}}, {"label": "micra", "text": "", "points": [[8.823790397451331, 415.0062111801242], [166.93650747114643, 487.4248816185966]], "group_id": null, "shape_type": "rectangle", "flags": {}}], "imagePath": "20230817114747F-2.JPG", "imageData": null, "imageHeight": 512, "imageWidth": 512, "text": ""}