{"version": "0.3.3", "flags": {}, "shapes": [{"label": "bank_name", "text": "", "points": [[10.321493358300696, 28.587535433385256], [168.6143523124037, 113.4200503054258]], "group_id": null, "shape_type": "rectangle", "flags": {}}, {"label": "date", "text": "", "points": [[362.36081689976004, 38.8083203577275], [501.17916008348453, 94.00055894917558]], "group_id": null, "shape_type": "rectangle", "flags": {}}, {"label": "amount", "text": "", "points": [[365.856242807264, 165.54605341957122], [502.677199758129, 214.60582105641396]], "group_id": null, "shape_type": "rectangle", "flags": {}}, {"label": "sign", "text": "", "points": [[234.52809799676209, 237.0915478899669], [497.6837341759807, 368.9396734139817]], "group_id": null, "shape_type": "rectangle", "flags": {}}, {"label": "micra", "text": "", "points": [[13.816919265804549, 432.3085399449035], [167.61565919597402, 477.2799936120094]], "group_id": null, "shape_type": "rectangle", "flags": {}}, {"label": "acc_info", "text": "", "points": [[20.308424522597416, 252.4227252764802], [220.04704780853186, 375.07214436858703]], "group_id": null, "shape_type": "rectangle", "flags": {}}, {"label": "pay_to", "text": "", "points": [[8.823453683656188, 121.5966782448996], [382.33467922835354, 163.50189643470276]], "group_id": null, "shape_type": "rectangle", "flags": {}}, {"label": "amount_words", "text": "", "points": [[11.320186474730368, 160.4356609574001], [334.8967561979441, 239.1357048748353]], "group_id": null, "shape_type": "rectangle", "flags": {}}], "imagePath": "20230814121718F-2.JPG", "imageData": null, "imageHeight": 512, "imageWidth": 512, "text": ""}